[
{
"team": "Argentina",
"elo": 2215.1
},
{
"team": "Spain",
"elo": 2186.5
},
{
"team": "France",
"elo": 2147.2
},
{
"team": "England",
"elo": 2113.1
},
{
"team": "Colombia",
"elo": 2076.2
},
{
"team": "Brazil",
"elo": 2067.1
},
{
"team": "Netherlands",
"elo": 2034.8
},
{
"team": "Germany",
"elo": 2032.1
},
{
"team": "Portugal",
"elo": 2008.2
},
{
"team": "Morocco",
"elo": 2007.4
},
{
"team": "Japan",
"elo": 2007.1
},
{
"team": "Norway",
"elo": 1999.2
},
{
"team": "Mexico",
"elo": 1994.4
},
{
"team": "Switzerland",
"elo": 1951.5
},
{
"team": "Ecuador",
"elo": 1951.4
},
{
"team": "Belgium",
"elo": 1948.8
},
{
"team": "Croatia",
"elo": 1930.9
},
{
"team": "Uruguay",
"elo": 1930.1
},
{
"team": "Italy",
"elo": 1915.9
},
{
"team": "United States",
"elo": 1914.2
},
{
"team": "Denmark",
"elo": 1912.9
},
{
"team": "Australia",
"elo": 1907.9
},
{
"team": "Austria",
"elo": 1906.3
},
{
"team": "Paraguay",
"elo": 1895.8
},
{
"team": "Iran",
"elo": 1887.1
},
{
"team": "Algeria",
"elo": 1885.8
},
{
"team": "South Korea",
"elo": 1884.2
},
{
"team": "Canada",
"elo": 1880.1
},
{
"team": "Nigeria",
"elo": 1879.8
},
{
"team": "Turkey",
"elo": 1872.7
},
{
"team": "Yugoslavia",
"elo": 1872.1
},
{
"team": "Senegal",
"elo": 1867.6
},
{
"team": "Egypt",
"elo": 1854.7
},
{
"team": "Ukraine",
"elo": 1841.2
},
{
"team": "Ivory Coast",
"elo": 1841.2
},
{
"team": "Russia",
"elo": 1840.0
},
{
"team": "Scotland",
"elo": 1830.6
},
{
"team": "Venezuela",
"elo": 1817.4
},
{
"team": "Jersey",
"elo": 1805.3
},
{
"team": "Czechoslovakia",
"elo": 1803.4
}
]