[
  {
    "team": "Spain",
    "R32": 0.998,
    "R16": 0.8492,
    "QF": 0.672,
    "SF": 0.5057,
    "F": 0.3684,
    "champion": 0.2546
  },
  {
    "team": "Argentina",
    "R32": 0.988,
    "R16": 0.8254,
    "QF": 0.6327,
    "SF": 0.4634,
    "F": 0.3236,
    "champion": 0.2129
  },
  {
    "team": "France",
    "R32": 0.9678,
    "R16": 0.7398,
    "QF": 0.508,
    "SF": 0.3271,
    "F": 0.1931,
    "champion": 0.1049
  },
  {
    "team": "England",
    "R32": 0.9793,
    "R16": 0.7111,
    "QF": 0.4475,
    "SF": 0.2685,
    "F": 0.1488,
    "champion": 0.0721
  },
  {
    "team": "Brazil",
    "R32": 0.9589,
    "R16": 0.6639,
    "QF": 0.4056,
    "SF": 0.2281,
    "F": 0.1153,
    "champion": 0.0539
  },
  {
    "team": "Colombia",
    "R32": 0.9377,
    "R16": 0.6361,
    "QF": 0.3897,
    "SF": 0.2147,
    "F": 0.1093,
    "champion": 0.0514
  },
  {
    "team": "Portugal",
    "R32": 0.92,
    "R16": 0.5766,
    "QF": 0.3228,
    "SF": 0.1642,
    "F": 0.0737,
    "champion": 0.0307
  },
  {
    "team": "Ecuador",
    "R32": 0.9622,
    "R16": 0.6042,
    "QF": 0.3343,
    "SF": 0.1698,
    "F": 0.0754,
    "champion": 0.0294
  },
  {
    "team": "Netherlands",
    "R32": 0.9319,
    "R16": 0.5763,
    "QF": 0.3085,
    "SF": 0.1475,
    "F": 0.0647,
    "champion": 0.0243
  },
  {
    "team": "Germany",
    "R32": 0.9527,
    "R16": 0.5706,
    "QF": 0.2991,
    "SF": 0.1425,
    "F": 0.059,
    "champion": 0.023
  },
  {
    "team": "Japan",
    "R32": 0.9066,
    "R16": 0.5256,
    "QF": 0.2662,
    "SF": 0.1213,
    "F": 0.0503,
    "champion": 0.0177
  },
  {
    "team": "Mexico",
    "R32": 0.9832,
    "R16": 0.5857,
    "QF": 0.2886,
    "SF": 0.1275,
    "F": 0.0471,
    "champion": 0.0154
  },
  {
    "team": "Morocco",
    "R32": 0.8895,
    "R16": 0.4936,
    "QF": 0.2482,
    "SF": 0.1096,
    "F": 0.0447,
    "champion": 0.0144
  },
  {
    "team": "Uruguay",
    "R32": 0.9236,
    "R16": 0.4795,
    "QF": 0.2344,
    "SF": 0.1001,
    "F": 0.0391,
    "champion": 0.0142
  },
  {
    "team": "Belgium",
    "R32": 0.9126,
    "R16": 0.5168,
    "QF": 0.2457,
    "SF": 0.1033,
    "F": 0.0381,
    "champion": 0.0126
  },
  {
    "team": "Switzerland",
    "R32": 0.9628,
    "R16": 0.524,
    "QF": 0.2415,
    "SF": 0.1007,
    "F": 0.0374,
    "champion": 0.011
  },
  {
    "team": "Croatia",
    "R32": 0.8911,
    "R16": 0.4632,
    "QF": 0.2161,
    "SF": 0.0923,
    "F": 0.0335,
    "champion": 0.0101
  },
  {
    "team": "Turkey",
    "R32": 0.7649,
    "R16": 0.4117,
    "QF": 0.1926,
    "SF": 0.0809,
    "F": 0.0282,
    "champion": 0.0098
  },
  {
    "team": "Norway",
    "R32": 0.7995,
    "R16": 0.3983,
    "QF": 0.1825,
    "SF": 0.0756,
    "F": 0.0289,
    "champion": 0.0091
  },
  {
    "team": "Paraguay",
    "R32": 0.6641,
    "R16": 0.3113,
    "QF": 0.1231,
    "SF": 0.0428,
    "F": 0.0134,
    "champion": 0.004
  },
  {
    "team": "Iran",
    "R32": 0.8043,
    "R16": 0.3592,
    "QF": 0.1419,
    "SF": 0.0465,
    "F": 0.014,
    "champion": 0.0037
  },
  {
    "team": "Senegal",
    "R32": 0.7046,
    "R16": 0.3149,
    "QF": 0.1336,
    "SF": 0.0475,
    "F": 0.014,
    "champion": 0.0037
  },
  {
    "team": "Australia",
    "R32": 0.6129,
    "R16": 0.271,
    "QF": 0.105,
    "SF": 0.0362,
    "F": 0.0101,
    "champion": 0.0032
  },
  {
    "team": "Canada",
    "R32": 0.9828,
    "R16": 0.4576,
    "QF": 0.1737,
    "SF": 0.0544,
    "F": 0.0149,
    "champion": 0.0031
  },
  {
    "team": "Austria",
    "R32": 0.6623,
    "R16": 0.2763,
    "QF": 0.1061,
    "SF": 0.0348,
    "F": 0.0101,
    "champion": 0.0027
  },
  {
    "team": "South Korea",
    "R32": 0.7975,
    "R16": 0.3225,
    "QF": 0.1172,
    "SF": 0.0393,
    "F": 0.0118,
    "champion": 0.0024
  },
  {
    "team": "Algeria",
    "R32": 0.6339,
    "R16": 0.2514,
    "QF": 0.0935,
    "SF": 0.0292,
    "F": 0.0082,
    "champion": 0.0016
  },
  {
    "team": "United States",
    "R32": 0.7266,
    "R16": 0.2591,
    "QF": 0.0751,
    "SF": 0.0175,
    "F": 0.004,
    "champion": 0.0011
  },
  {
    "team": "Scotland",
    "R32": 0.6079,
    "R16": 0.2064,
    "QF": 0.0629,
    "SF": 0.017,
    "F": 0.0037,
    "champion": 0.0008
  },
  {
    "team": "Uzbekistan",
    "R32": 0.4756,
    "R16": 0.1527,
    "QF": 0.0436,
    "SF": 0.0111,
    "F": 0.0027,
    "champion": 0.0006
  },
  {
    "team": "Panama",
    "R32": 0.6979,
    "R16": 0.2497,
    "QF": 0.0766,
    "SF": 0.0197,
    "F": 0.0042,
    "champion": 0.0006
  },
  {
    "team": "Czech Republic",
    "R32": 0.6173,
    "R16": 0.18,
    "QF": 0.0491,
    "SF": 0.0103,
    "F": 0.0023,
    "champion": 0.0003
  },
  {
    "team": "Egypt",
    "R32": 0.6132,
    "R16": 0.1998,
    "QF": 0.0534,
    "SF": 0.0126,
    "F": 0.0024,
    "champion": 0.0003
  },
  {
    "team": "Sweden",
    "R32": 0.4579,
    "R16": 0.1202,
    "QF": 0.0263,
    "SF": 0.0053,
    "F": 0.0008,
    "champion": 0.0001
  },
  {
    "team": "Iraq",
    "R32": 0.2387,
    "R16": 0.0551,
    "QF": 0.0115,
    "SF": 0.0018,
    "F": 0.0004,
    "champion": 0.0001
  },
  {
    "team": "New Zealand",
    "R32": 0.399,
    "R16": 0.09,
    "QF": 0.0162,
    "SF": 0.0027,
    "F": 0.0004,
    "champion": 0.0001
  },
  {
    "team": "Ivory Coast",
    "R32": 0.6494,
    "R16": 0.203,
    "QF": 0.054,
    "SF": 0.0134,
    "F": 0.0023,
    "champion": 0.0001
  },
  {
    "team": "Saudi Arabia",
    "R32": 0.3118,
    "R16": 0.0556,
    "QF": 0.009,
    "SF": 0.0013,
    "F": 0.0001,
    "champion": 0.0001
  },
  {
    "team": "Jordan",
    "R32": 0.3471,
    "R16": 0.0917,
    "QF": 0.0218,
    "SF": 0.0038,
    "F": 0.0005,
    "champion": 0.0001
  },
  {
    "team": "DR Congo",
    "R32": 0.3426,
    "R16": 0.0883,
    "QF": 0.0198,
    "SF": 0.0033,
    "F": 0.0004,
    "champion": 0.0001
  },
  {
    "team": "Tunisia",
    "R32": 0.3836,
    "R16": 0.0889,
    "QF": 0.0191,
    "SF": 0.0032,
    "F": 0.0004,
    "champion": 0.0001
  },
  {
    "team": "Haiti",
    "R32": 0.2397,
    "R16": 0.0483,
    "QF": 0.0084,
    "SF": 0.0013,
    "F": 0.0003,
    "champion": 0.0001
  },
  {
    "team": "Cape Verde",
    "R32": 0.2409,
    "R16": 0.0362,
    "QF": 0.0046,
    "SF": 0.0004,
    "F": 0.0001,
    "champion": 0.0
  },
  {
    "team": "Qatar",
    "R32": 0.1976,
    "R16": 0.0191,
    "QF": 0.0015,
    "SF": 0.0,
    "F": 0.0,
    "champion": 0.0
  },
  {
    "team": "Bosnia and Herzegovina",
    "R32": 0.4199,
    "R16": 0.0657,
    "QF": 0.0079,
    "SF": 0.0008,
    "F": 0.0001,
    "champion": 0.0
  },
  {
    "team": "Ghana",
    "R32": 0.1441,
    "R16": 0.0185,
    "QF": 0.0024,
    "SF": 0.0003,
    "F": 0.0,
    "champion": 0.0
  },
  {
    "team": "South Africa",
    "R32": 0.2606,
    "R16": 0.0416,
    "QF": 0.0052,
    "SF": 0.0005,
    "F": 0.0,
    "champion": 0.0
  },
  {
    "team": "Curaçao",
    "R32": 0.1356,
    "R16": 0.0143,
    "QF": 0.0014,
    "SF": 0.0003,
    "F": 0.0001,
    "champion": 0.0
  }
]